README.md
setup.py
Binance_Wrapper/Binance_Wrapper_Functions.py
Binance_Wrapper/__init__.py
Binance_Wrapper.egg-info/PKG-INFO
Binance_Wrapper.egg-info/SOURCES.txt
Binance_Wrapper.egg-info/dependency_links.txt
Binance_Wrapper.egg-info/not-zip-safe
Binance_Wrapper.egg-info/top_level.txt