Metadata-Version: 1.0
Name: Binance-Wrapper
Version: 0.1
Summary: The FUnctions to Make using the Binance API easier and cleaner
Home-page: https://github.com/mario-likes-camels/Binance_Wrapper
Author: Patrick
Author-email: hi_in@hotmail.com
License: MIT
Platform: UNKNOWN
